polar2grid/__init__.py
polar2grid/__main__.py
polar2grid/_glue_argparser.py
polar2grid/add_coastlines.py
polar2grid/add_colormap.py
polar2grid/compare.py
polar2grid/debug_data.py
polar2grid/glue.py
polar2grid/composites/__init__.py
polar2grid/composites/enhanced.py
polar2grid/core/__init__.py
polar2grid/core/containers.py
polar2grid/core/dtype.py
polar2grid/core/script_utils.py
polar2grid/enhancements/__init__.py
polar2grid/enhancements/shared.py
polar2grid/etc/pyspectral.yaml
polar2grid/etc/resampling.yaml
polar2grid/etc/colormaps/IFR_PROB.cmap
polar2grid/etc/colormaps/LIFR_PROB.cmap
polar2grid/etc/colormaps/MVFR_PROB.cmap
polar2grid/etc/colormaps/abi_l2_modified_cloud_top.cmap
polar2grid/etc/colormaps/amsr2_36h.cmap
polar2grid/etc/colormaps/amsr2_89h.cmap
polar2grid/etc/colormaps/gridded_data.cmap
polar2grid/etc/colormaps/hsl256_no_black.cmap
polar2grid/etc/colormaps/p2g_sst_palette.txt
polar2grid/etc/colormaps/tropix_no_white.cmap
polar2grid/etc/colormaps/viirs_edr_flood_water_detection.cmap
polar2grid/etc/composites/abi.yaml
polar2grid/etc/composites/ahi.yaml
polar2grid/etc/composites/mersi-2.yaml
polar2grid/etc/composites/modis.yaml
polar2grid/etc/composites/viirs.yaml
polar2grid/etc/enhancements/abi.yaml
polar2grid/etc/enhancements/agri.yaml
polar2grid/etc/enhancements/ahi.yaml
polar2grid/etc/enhancements/ami.yaml
polar2grid/etc/enhancements/generic.yaml
polar2grid/etc/enhancements/mersi-2.yaml
polar2grid/etc/enhancements/modis.yaml
polar2grid/etc/enhancements/viirs.yaml
polar2grid/etc/readers/mirs.yaml
polar2grid/etc/writers/awips_tiled.yaml
polar2grid/etc/writers/binary.yaml
polar2grid/etc/writers/hdf5.yaml
polar2grid/filters/__init__.py
polar2grid/filters/_base.py
polar2grid/filters/_filter_scene.py
polar2grid/filters/_utils.py
polar2grid/filters/day_night.py
polar2grid/filters/resample_coverage.py
polar2grid/fonts/Vera.ttf
polar2grid/fonts/__init__.py
polar2grid/grids/__init__.py
polar2grid/grids/config_helper.py
polar2grid/grids/grids.yaml
polar2grid-3.2.0.dist-info/METADATA
polar2grid-3.2.0.dist-info/WHEEL
polar2grid-3.2.0.dist-info/entry_points.txt
polar2grid-3.2.0.dist-info/licenses/LICENSE.txt
polar2grid-3.2.0.dist-info/RECORD
