Metadata-Version: 2.4
Name: polar2grid
Version: 3.2.0
Summary: Library and scripts to remap satellite data to a gridded image
Project-URL: Documentation, https://www.ssec.wisc.edu/software/polar2grid/
Project-URL: Home-page, https://cimss.ssec.wisc.edu/cspp/
Project-URL: Download-URL, https://pypi.org/project/polar2grid/
Project-URL: Project-URL, https://github.com/ssec/polar2grid/
Author-email: David Hoese <david.hoese@ssec.wisc.edu>
License: GPLv3
License-File: LICENSE.txt
Classifier: Development Status :: 5 - Production/Stable
Classifier: Intended Audience :: Science/Research
Classifier: License :: OSI Approved :: GNU General Public License v3 (GPLv3)
Classifier: Operating System :: MacOS :: MacOS X
Classifier: Operating System :: Microsoft :: Windows
Classifier: Operating System :: POSIX :: Linux
Classifier: Programming Language :: Python
Classifier: Programming Language :: Python :: 3
Classifier: Programming Language :: Python :: Implementation :: CPython
Classifier: Topic :: Scientific/Engineering
Classifier: Topic :: Scientific/Engineering :: Atmospheric Science
Classifier: Topic :: Scientific/Engineering :: GIS
Requires-Python: >=3.10
Requires-Dist: h5py
Requires-Dist: netcdf4
Requires-Dist: rasterio
Requires-Dist: satpy
Provides-Extra: all
Requires-Dist: matplotlib; extra == 'all'
Requires-Dist: pycoast; extra == 'all'
Requires-Dist: pydecorate; extra == 'all'
Requires-Dist: pytest; extra == 'all'
Requires-Dist: rst2pdf; extra == 'all'
Requires-Dist: sphinx; extra == 'all'
Requires-Dist: sphinx-argparse; extra == 'all'
Requires-Dist: sphinxcontrib-apidoc; extra == 'all'
Provides-Extra: coastlines
Requires-Dist: pycoast; extra == 'coastlines'
Requires-Dist: pydecorate; extra == 'coastlines'
Provides-Extra: docs
Requires-Dist: pytest; extra == 'docs'
Requires-Dist: rst2pdf; extra == 'docs'
Requires-Dist: sphinx; extra == 'docs'
Requires-Dist: sphinx-argparse; extra == 'docs'
Requires-Dist: sphinxcontrib-apidoc; extra == 'docs'
Provides-Extra: tests
Requires-Dist: pytest; extra == 'tests'
Provides-Extra: utils
Requires-Dist: matplotlib; extra == 'utils'
